Tin_hieu_hinh_sin/Tin_hieu_hinh_sin.srcs/sources_1/new/sine_wave_generator.v
`timescale 1ns / 1ps
//////////////////////////////////////////////////////////////////////////////////
// Company: 
// Engineer: 
// 
// Create Date: 03/24/2025 10:02:31 AM
// Design Name: 
// Module Name: sine_wave_generator
// Project Name: 
// Target Devices: 
// Tool Versions: 
// Description: 
// 
// Dependencies: 
// 
// Revision:
// Revision 0.01 - File Created
// Additional Comments:
// 
//////////////////////////////////////////////////////////////////////////////////

module sine_wave_generator (
    input wire clk,          // Clock ??u vào
    input wire rst_n,//key 1        // Reset active-low
    input down, // key 3
    input up,    // key 2
    output reg [7:0] sine_out // Tín hi?u sin ??u ra (8-bit)
);
//cai dat nut up (key 2)
reg [25:0] counter_up;// Dem counter_up chong rung khi nhan up (key2)
always @(posedge clk) begin
    if(!rst_n) begin
        counter_up <= 26'd0;
    end
    else begin
        if(up)  // Neu ko nhan up (key 2)
            counter_up <= 0;
        
        else begin // Neu nhan up
            if(counter_up == 26'h4D7840) 
                counter_up <= 0;
            else 
                counter_up <= counter_up + 1;
        end
    end    
end
//cai dat nut down (key 3)
reg [25:0] counter_down;// Dem counter_down chong rung khi nhan down (key 3)
always @(posedge clk) begin
    if(!rst_n) begin
        counter_down <= 26'd0;
    end
    else begin
        if(down)  // Neu ko nhan up (key 2)
            counter_down <= 0;
        
        else begin // Neu nhan up
            if(counter_down == 26'h4D7840) 
                counter_down <= 0;
            else 
                counter_down <= counter_down + 1;
        end
    end    
end

    // ??nh ngh?a b?ng tra c?u (LUT) cho 1 chu k? sin
    // S? m?u: 256 (8-bit index), giá tr? sin t? 0 ??n 255 (8-bit)
    reg [7:0] sine_table [0:255];
    reg [7:0] phase; // B? ??m pha (index cho LUT)

    // Kh?i t?o b?ng tra c?u (LUT) v?i giá tr? sin
    initial begin
        sine_table[0] = 128  ; sine_table[1] = 131  ; sine_table[2] = 134  ; sine_table[3] = 137;
        sine_table[4] = 140  ; sine_table[5] = 143  ; sine_table[6] = 146  ; sine_table[7] = 149;
        sine_table[8] = 152  ; sine_table[9] = 155  ; sine_table[10] = 158 ; sine_table[11] = 161;
        sine_table[12] = 164 ; sine_table[13] = 167 ; sine_table[14] = 170 ; sine_table[15] = 173;
        sine_table[16] = 176 ; sine_table[17] = 179 ; sine_table[18] = 182 ; sine_table[19] = 185;
        sine_table[20] = 188 ; sine_table[21] = 191 ; sine_table[22] = 193 ; sine_table[23] = 196;
        sine_table[24] = 199 ; sine_table[25] = 202 ; sine_table[26] = 204 ; sine_table[27] = 207;
        sine_table[28] = 209 ; sine_table[29] = 211 ; sine_table[30] = 213 ; sine_table[31] = 215;
        sine_table[32] = 218 ; sine_table[33] = 220 ; sine_table[34] = 222 ; sine_table[35] = 224;
        sine_table[36] = 226 ; sine_table[37] = 228 ; sine_table[38] = 230 ; sine_table[39] = 232;
        sine_table[40] = 234 ; sine_table[41] = 235 ; sine_table[42] = 237 ; sine_table[43] = 239;
        sine_table[44] = 240 ; sine_table[45] = 241 ; sine_table[46] = 243 ; sine_table[47] = 244;
        sine_table[48] = 245 ; sine_table[49] = 246 ; sine_table[50] = 248 ; sine_table[51] = 249;
        sine_table[52] = 250 ; sine_table[53] = 250 ; sine_table[54] = 251 ; sine_table[55] = 252;
        sine_table[56] = 253 ; sine_table[57] = 253 ; sine_table[58] = 254 ; sine_table[59] = 254;
        sine_table[60] = 254 ; sine_table[61] = 255 ; sine_table[62] = 255 ; sine_table[63] = 255;//doan sau ao vl
        sine_table[64] = 255 ; sine_table[65] = 255 ; sine_table[66] = 255 ; sine_table[67] = 254;
        sine_table[68] = 254 ; sine_table[69] = 254 ; sine_table[70] = 253 ; sine_table[71] = 253;
        sine_table[72] = 252 ; sine_table[73] = 251 ; sine_table[74] = 250 ; sine_table[75] = 250;
        sine_table[76] = 249 ; sine_table[77] = 248 ; sine_table[78] = 246 ; sine_table[79] = 245;
        sine_table[80] = 244 ; sine_table[81] = 243 ; sine_table[82] = 241 ; sine_table[83] = 240;
        sine_table[84] = 239 ; sine_table[85] = 237 ; sine_table[86] = 235 ; sine_table[87] = 234;
        sine_table[88] = 232 ; sine_table[89] = 230 ; sine_table[90] = 228 ; sine_table[91] = 226;
        sine_table[92] = 224 ; sine_table[93] = 222 ; sine_table[94] = 220 ; sine_table[95] = 218;
        sine_table[96] = 215 ; sine_table[97] = 213 ; sine_table[98] = 211 ; sine_table[99] = 209;
        sine_table[100] = 207; sine_table[101] = 204; sine_table[102] = 202; sine_table[103] = 199;
        sine_table[104] = 196; sine_table[105] = 193; sine_table[106] = 191; sine_table[107] = 188;
        sine_table[108] = 185; sine_table[109] = 182; sine_table[110] = 179; sine_table[111] = 176;
        sine_table[112] = 173; sine_table[113] = 170; sine_table[114] = 167; sine_table[115] = 164;
        sine_table[116] = 161; sine_table[117] = 158; sine_table[118] = 155; sine_table[119] = 152;
        sine_table[120] = 149; sine_table[121] = 146; sine_table[122] = 143; sine_table[123] = 140;
        sine_table[124] = 137; sine_table[125] = 134; sine_table[126] = 131; sine_table[127] = 128;//
        sine_table[128] = 128; sine_table[129] = 125; sine_table[130] = 122; sine_table[131] = 119;
        sine_table[132] = 116; sine_table[133] = 113; sine_table[134] = 110; sine_table[135] = 106;
        sine_table[136] = 103; sine_table[137] = 100; sine_table[138] = 97; sine_table[139] = 94;
        sine_table[140] = 91; sine_table[141] = 88; sine_table[142] = 85; sine_table[143] = 82;
        sine_table[144] = 79; sine_table[145] = 77; sine_table[146] = 74; sine_table[147] = 71;
        sine_table[148] = 68; sine_table[149] = 65; sine_table[150] = 63; sine_table[151] = 60;
        sine_table[152] = 57; sine_table[153] = 55; sine_table[154] = 50; sine_table[155] = 47;
        sine_table[156] = 45; sine_table[157] = 43; sine_table[158] = 40; sine_table[159] = 38;
        sine_table[160] = 36; sine_table[161] = 34; sine_table[162] = 32; sine_table[163] = 30;
        sine_table[164] = 28; sine_table[165] = 26; sine_table[166] = 24; sine_table[167] = 22;
        sine_table[168] = 21; sine_table[169] = 20; sine_table[170] = 19; sine_table[171] = 17;
        sine_table[172] = 16; sine_table[173] = 15; sine_table[174] = 13; sine_table[175] = 12;
        sine_table[176] = 11; sine_table[177] = 10; sine_table[178] = 8; sine_table[179] = 7;
        sine_table[180] = 6; sine_table[181] = 6; sine_table[182] = 5; sine_table[183] = 4;
        sine_table[184] = 3; sine_table[185] = 3; sine_table[186] = 2; sine_table[187] = 2;
        sine_table[188] = 2; sine_table[189] = 1; sine_table[190] = 1; sine_table[191] = 1;//
        sine_table[192] = 1; sine_table[193] = 1; sine_table[194] = 1; sine_table[195] = 2;
        sine_table[196] = 2; sine_table[197] = 2; sine_table[198] = 3; sine_table[199] = 3;
        sine_table[200] = 4; sine_table[201] = 5; sine_table[202] = 6; sine_table[203] = 6;
        sine_table[204] = 7; sine_table[205] = 8; sine_table[206] = 10; sine_table[207] = 11;
        sine_table[208] = 12; sine_table[209] = 13; sine_table[210] = 15; sine_table[211] = 16;
        sine_table[212] = 17; sine_table[213] = 19; sine_table[214] = 20; sine_table[215] = 21;
        sine_table[216] = 22; sine_table[217] = 24; sine_table[218] = 26; sine_table[219] = 28;
        sine_table[220] = 30; sine_table[221] = 32; sine_table[222] = 34; sine_table[223] = 36;
        sine_table[224] = 38; sine_table[225] = 40; sine_table[226] = 43; sine_table[227] = 45;
        sine_table[228] = 47; sine_table[229] = 50; sine_table[230] = 55; sine_table[231] = 57;
        sine_table[232] = 60; sine_table[233] = 63; sine_table[234] = 65; sine_table[235] = 68;
        sine_table[236] = 71; sine_table[237] = 74; sine_table[238] = 77; sine_table[239] = 79;
        sine_table[240] = 82; sine_table[241] = 85; sine_table[242] = 88; sine_table[243] = 91;
        sine_table[244] = 94; sine_table[245] = 97; sine_table[246] = 100; sine_table[247] = 103;
        sine_table[248] = 106; sine_table[249] = 110; sine_table[250] = 113; sine_table[251] = 116;
        sine_table[252] = 119; sine_table[253] = 122; sine_table[254] = 125; sine_table[255] = 128;
    end

    // B? ??m pha ?? truy c?p LUT
    reg [15:0] clk_div,counter;
always @(posedge clk) begin
    if (!rst_n) begin
        counter <= 16'd10; // Giá tr? kh?i t?o h?p lý
    end else begin
        if (counter_up == 26'h4D7840) begin
            if (counter > 1)// Gioi han tan so toi thieu 
                counter <= counter - 1; // Tang tan so
        end else if (counter_down == 26'h4D7840) begin
            if (counter < 5000) // Gioi han tan so toi da
                counter <= counter + 1; // Giam tan so
        end
    end
end
    
always @(posedge clk or negedge rst_n) begin
    if (!rst_n) begin
        clk_div <= 0;
        phase <= 0;
        sine_out <= 8'd128;
    end
    else begin
        clk_div <= clk_div + 1;
        if (clk_div == counter) begin
            clk_div <= 0;   
            sine_out <= sine_table[phase]; // Truy c?p tr?c ti?p LUT
            if(phase < 255)
                phase <= phase + 1;
            else
                phase <= 0;
        end
    end
end

endmodule

Tin_hieu_hinh_sin/Tin_hieu_hinh_sin.srcs/sim_1/new/tb_sine_wave_generator.v
`timescale 1ns / 1ps
//////////////////////////////////////////////////////////////////////////////////
// Company: 
// Engineer: 
// 
// Create Date: 03/24/2025 10:03:58 AM
// Design Name: 
// Module Name: tb_sine_wave_generator
// Project Name: 
// Target Devices: 
// Tool Versions: 
// Description: 
// 
// Dependencies: 
// 
// Revision:
// Revision 0.01 - File Created
// Additional Comments:
// 
//////////////////////////////////////////////////////////////////////////////////


module tb_sine_wave_generator(

    );

    // dau vào
    reg clk;
    reg rst_n;
    // dau ra
    wire [7:0] sine_out;

    // Khoi tao module
    sine_wave_generator uut (
        .clk(clk),
        .rst_n(rst_n),
        .sine_out(sine_out)
    );

    // Tao clock 500MHz (chu ki 2ns)
    initial begin
        clk = 0;
        forever #1 clk = ~clk; // Chu ki 2ns
    end

    // Kich ban kiem tra
    initial begin
        // Reset ban dau
        rst_n = 0;
        #20;
        rst_n = 1;

        // Chay mô phong trong 100 chu ki sin
        #5200; // 10 chu ki sin (256 * 2ns * 100)
        $finish;
    end

    // Ghi ket qua ra file de xem dang sóng
    initial begin
        $dumpfile("sine_wave.vcd");
        $dumpvars(0, tb_sine_wave_generator);
    end

endmodule

Tin_hieu_hinh_sin/Tin_hieu_hinh_sin.sim/sim_1/behav/xsim/sine_wave.vcd
$date
   Mon May 19 23:18:32 2025
$end
$version
  2019.1
$end
$timescale
  1ps
$end
$scope module tb_sine_wave_generator $end
$var reg 1 ! clk $end
$var reg 1 " rst_n $end
$var wire 8 # sine_out [7:0] $end
$scope module uut $end
$var wire 1 $ clk $end
$var wire 1 % rst_n $end
$var wire 1 & down $end
$var wire 1 ' up $end
$var reg 8 ( sine_out [7:0] $end
$var reg 26 ) counter_up [25:0] $end
$var reg 26 * counter_down [25:0] $end
$var reg 8 + phase [7:0] $end
$var reg 16 , clk_div [15:0] $end
$var reg 16 - counter [15:0] $end
$upscope $end
$upscope $end
$enddefinitions $end
#0
$dumpvars
0!
0"
b10000000 #
0$
0%
z&
z'
b10000000 (
bx )
bx *
b0 +
b0 ,
bx -
$end
#1000
1!
1$
b0 )
b0 *
b1010 -
#2000
0!
0$
#3000
1!
1$
#4000
0!
0$
#5000
1!
1$
#6000
0!
0$
#7000
1!
1$
#8000
0!
0$
#9000
1!
1$
#10000
0!
0$
#11000
1!
1$
#12000
0!
0$
#13000
1!
1$
#14000
0!
0$
#15000
1!
1$
#16000
0!
0$
#17000
1!
1$
#18000
0!
0$
#19000
1!
1$
#20000
0!
1"
0$
1%
#21000
1!
1$
b1 )
b1 *
b1 ,
#22000
0!
0$
#23000
1!
1$
b10 )
b10 *
b10 ,
#24000
0!
0$
#25000
1!
1$
b11 )
b11 *
b11 ,
#26000
0!
0$
#27000
1!
1$
b100 )
b100 *
b100 ,
#28000
0!
0$
#29000
1!
1$
b101 )
b101 *
b101 ,
#30000
0!
0$
#31000
1!
1$
b110 )
b110 *
b110 ,
#32000
0!
0$
#33000
1!
1$
b111 )
b111 *
b111 ,
#34000
0!
0$
#35000
1!
1$
b1000 )
b1000 *
b1000 ,
#36000
0!
0$
#37000
1!
1$
b1001 )
b1001 *
b1001 ,
#38000
0!
0$
#39000
1!
1$
b1010 )
b1010 *
b1010 ,
#40000
0!
0$
#41000
1!
1$
b1011 )
b1011 *
b1 +
b0 ,
#42000
0!
0$
#43000
1!
1$
b1100 )
b1100 *
b1 ,
#44000
0!
0$
#45000
1!
1$
b1101 )
b1101 *
b10 ,
#46000
0!
0$
#47000
1!
1$
b1110 )
b1110 *
b11 ,
#48000
0!
0$
#49000
1!
1$
b1111 )
b1111 *
b100 ,
#50000
0!
0$
#51000
1!
1$
b10000 )
b10000 *
b101 ,
#52000
0!
0$
#53000
1!
1$
b10001 )
b10001 *
b110 ,
#54000
0!
0$
#55000
1!
1$
b10010 )
b10010 *
b111 ,
#56000
0!
0$
#57000
1!
1$
b10011 )
b10011 *
b1000 ,
#58000
0!
0$
#59000
1!
1$
b10100 )
b10100 *
b1001 ,
#60000
0!
0$
#61000
1!
1$
b10101 )
b10101 *
b1010 ,
#62000
0!
0$
#63000
1!
b10000011 #
1$
b10000011 (
b10110 )
b10110 *
b10 +
b0 ,
#64000
0!
0$
#65000
1!
1$
b10111 )
b10111 *
b1 ,
#66000
0!
0$
#67000
1!
1$
b11000 )
b11000 *
b10 ,
#68000
0!
0$
#69000
1!
1$
b11001 )
b11001 *
b11 ,
#70000
0!
0$
#71000
1!
1$
b11010 )
b11010 *
b100 ,
#72000
0!
0$
#73000
1!
1$
b11011 )
b11011 *
b101 ,
#74000
0!
0$
#75000
1!
1$
b11100 )
b11100 *
b110 ,
#76000
0!
0$
#77000
1!
1$
b11101 )
b11101 *
b111 ,
#78000
0!
0$
#79000
1!
1$
b11110 )
b11110 *
b1000 ,
#80000
0!
0$
#81000
1!
1$
b11111 )
b11111 *
b1001 ,
#82000
0!
0$
#83000
1!
1$
b100000 )
b100000 *
b1010 ,
#84000
0!
0$
#85000
1!
b10000110 #
1$
b10000110 (
b100001 )
b100001 *
b11 +
b0 ,
#86000
0!
0$
#87000
1!
1$
b100010 )
b100010 *
b1 ,
#88000
0!
0$
#89000
1!
1$
b100011 )
b100011 *
b10 ,
#90000
0!
0$
#91000
1!
1$
b100100 )
b100100 *
b11 ,
#92000
0!
0$
#93000
1!
1$
b100101 )
b100101 *
b100 ,
#94000
0!
0$
#95000
1!
1$
b100110 )
b100110 *
b101 ,
#96000
0!
0$
#97000
1!
1$
b100111 )
b100111 *
b110 ,
#98000
0!
0$
#99000
1!
1$
b101000 )
b101000 *
b111 ,
#100000
0!
0$
#101000
1!
1$
b101001 )
b101001 *
b1000 ,
#102000
0!
0$
#103000
1!
1$
b101010 )
b101010 *
b1001 ,
#104000
0!
0$
#105000
1!
1$
b101011 )
b101011 *
b1010 ,
#106000
0!
0$
#107000
1!
b10001001 #
1$
b10001001 (
b101100 )
b101100 *
b100 +
b0 ,
#108000
0!
0$
#109000
1!
1$
b101101 )
b101101 *
b1 ,
#110000
0!
0$
#111000
1!
1$
b101110 )
b101110 *
b10 ,
#112000
0!
0$
#113000
1!
1$
b101111 )
b101111 *
b11 ,
#114000
0!
0$
#115000
1!
1$
b110000 )
b110000 *
b100 ,
#116000
0!
0$
#117000
1!
1$
b110001 )
b110001 *
b101 ,
#118000
0!
0$
#119000
1!
1$
b110010 )
b110010 *
b110 ,
#120000
0!
0$
#121000
1!
1$
b110011 )
b110011 *
b111 ,
#122000
0!
0$
#123000
1!
1$
b110100 )
b110100 *
b1000 ,
#124000
0!
0$
#125000
1!
1$
b110101 )
b110101 *
b1001 ,
#126000
0!
0$
#127000
1!
1$
b110110 )
b110110 *
b1010 ,
#128000
0!
0$
#129000
1!
b10001100 #
1$
b10001100 (
b110111 )
b110111 *
b101 +
b0 ,
#130000
0!
0$
#131000
1!
1$
b111000 )
b111000 *
b1 ,
#132000
0!
0$
#133000
1!
1$
b111001 )
b111001 *
b10 ,
#134000
0!
0$
#135000
1!
1$
b111010 )
b111010 *
b11 ,
#136000
0!
0$
#137000
1!
1$
b111011 )
b111011 *
b100 ,
#138000
0!
0$
#139000
1!
1$
b111100 )
b111100 *
b101 ,
#140000
0!
0$
#141000
1!
1$
b111101 )
b111101 *
b110 ,
#142000
0!
0$
#143000
1!
1$
b111110 )
b111110 *
b111 ,
#144000
0!
0$
#145000
1!
1$
b111111 )
b111111 *
b1000 ,
#146000
0!
0$
#147000
1!
1$
b1000000 )
b1000000 *
b1001 ,
#148000
0!
0$
#149000
1!
1$
b1000001 )
b1000001 *
b1010 ,
#150000
0!
0$
#151000
1!
b10001111 #
1$
b10001111 (
b1000010 )
b1000010 *
b110 +
b0 ,
#152000
0!
0$
#153000
1!
1$
b1000011 )
b1000011 *
b1 ,
#154000
0!
0$
#155000
1!
1$
b1000100 )
b1000100 *
b10 ,
#156000
0!
0$
#157000
1!
1$
b1000101 )
b1000101 *
b11 ,
#158000
0!
0$
#159000
1!
1$
b1000110 )
b1000110 *
b100 ,
#160000
0!
0$
#161000
1!
1$
b1000111 )
b1000111 *
b101 ,
#162000
0!
0$
#163000
1!
1$
b1001000 )
b1001000 *
b110 ,
#164000
0!
0$
#165000
1!
1$
b1001001 )
b1001001 *
b111 ,
#166000
0!
0$
#167000
1!
1$
b1001010 )
b1001010 *
b1000 ,
#168000
0!
0$
#169000
1!
1$
b1001011 )
b1001011 *
b1001 ,
#170000
0!
0$
#171000
1!
1$
b1001100 )
b1001100 *
b1010 ,
#172000
0!
0$
#173000
1!
b10010010 #
1$
b10010010 (
b1001101 )
b1001101 *
b111 +
b0 ,
#174000
0!
0$
#175000
1!
1$
b1001110 )
b1001110 *
b1 ,
#176000
0!
0$
#177000
1!
1$
b1001111 )
b1001111 *
b10 ,
#178000
0!
0$
#179000
1!
1$
b1010000 )
b1010000 *
b11 ,
#180000
0!
0$
#181000
1!
1$
b1010001 )
b1010001 *
b100 ,
#182000
0!
0$
#183000
1!
1$
b1010010 )
b1010010 *
b101 ,
#184000
0!
0$
#185000
1!
1$
b1010011 )
b1010011 *
b110 ,
#186000
0!
0$
#187000
1!
1$
b1010100 )
b1010100 *
b111 ,
#188000
0!
0$
#189000
1!
1$
b1010101 )
b1010101 *
b1000 ,
#190000
0!
0$
#191000
1!
1$
b1010110 )
b1010110 *
b1001 ,
#192000
0!
0$
#193000
1!
1$
b1010111 )
b1010111 *
b1010 ,
#194000
0!
0$
#195000
1!
b10010101 #
1$
b10010101 (
b1011000 )
b1011000 *
b1000 +
b0 ,
#196000
0!
0$
#197000
1!
1$
b1011001 )
b1011001 *
b1 ,
#198000
0!
0$
#199000
1!
1$
b1011010 )
b1011010 *
b10 ,
#200000
0!
0$
#201000
1!
1$
b1011011 )
b1011011 *
b11 ,
#202000
0!
0$
#203000
1!
1$
b1011100 )
b1011100 *
b100 ,
#204000
0!
0$
#205000
1!
1$
b1011101 )
b1011101 *
b101 ,
#206000
0!
0$
#207000
1!
1$
b1011110 )
b1011110 *
b110 ,
#208000
0!
0$
#209000
1!
1$
b1011111 )
b1011111 *
b111 ,
#210000
0!
0$
#211000
1!
1$
b1100000 )
b1100000 *
b1000 ,
#212000
0!
0$
#213000
1!
1$
b1100001 )
b1100001 *
b1001 ,
#214000
0!
0$
#215000
1!
1$
b1100010 )
b1100010 *
b1010 ,
#216000
0!
0$
#217000
1!
b10011000 #
1$
b10011000 (
b1100011 )
b1100011 *
b1001 +
b0 ,
#218000
0!
0$
#219000
1!
1$
b1100100 )
b1100100 *
b1 ,
#220000
0!
0$
#221000
1!
1$
b1100101 )
b1100101 *
b10 ,
#222000
0!
0$
#223000
1!
1$
b1100110 )
b1100110 *
b11 ,
#224000
0!
0$
#225000
1!
1$
b1100111 )
b1100111 *
b100 ,
#226000
0!
0$
#227000
1!
1$
b1101000 )
b1101000 *
b101 ,
#228000
0!
0$
#229000
1!
1$
b1101001 )
b1101001 *
b110 ,
#230000
0!
0$
#231000
1!
1$
b1101010 )
b1101010 *
b111 ,
#232000
0!
0$
#233000
1!
1$
b1101011 )
b1101011 *
b1000 ,
#234000
0!
0$
#235000
1!
1$
b1101100 )
b1101100 *
b1001 ,
#236000
0!
0$
#237000
1!
1$
b1101101 )
b1101101 *
b1010 ,
#238000
0!
0$
#239000
1!
b10011011 #
1$
b10011011 (
b1101110 )
b1101110 *
b1010 +
b0 ,
#240000
0!
0$
#241000
1!
1$
b1101111 )
b1101111 *
b1 ,
#242000
0!
0$
#243000
1!
1$
b1110000 )
b1110000 *
b10 ,
#244000
0!
0$
#245000
1!
1$
b1110001 )
b1110001 *
b11 ,
#246000
0!
0$
#247000
1!
1$
b1110010 )
b1110010 *
b100 ,
#248000
0!
0$
#249000
1!
1$
b1110011 )
b1110011 *
b101 ,
#250000
0!
0$
#251000
1!
1$
b1110100 )
b1110100 *
b110 ,
#252000
0!
0$
#253000
1!
1$
b1110101 )
b1110101 *
b111 ,
#254000
0!
0$
#255000
1!
1$
b1110110 )
b1110110 *
b1000 ,
#256000
0!
0$
#257000
1!
1$
b1110111 )
b1110111 *
b1001 ,
#258000
0!
0$
#259000
1!
1$
b1111000 )
b1111000 *
b1010 ,
#260000
0!
0$
#261000
1!
b10011110 #
1$
b10011110 (
b1111001 )
b1111001 *
b1011 +
b0 ,
#262000
0!
0$
#263000
1!
1$
b1111010 )
b1111010 *
b1 ,
#264000
0!
0$
#265000
1!
1$
b1111011 )
b1111011 *
b10 ,
#266000
0!
0$
#267000
1!
1$
b1111100 )
b1111100 *
b11 ,
#268000
0!
0$
#269000
1!
1$
b1111101 )
b1111101 *
b100 ,
#270000
0!
0$
#271000
1!
1$
b1111110 )
b1111110 *
b101 ,
#272000
0!
0$
#273000
1!
1$
b1111111 )
b1111111 *
b110 ,
#274000
0!
0$
#275000
1!
1$
b10000000 )
b10000000 *
b111 ,
#276000
0!
0$
#277000
1!
1$
b10000001 )
b10000001 *
b1000 ,
#278000
0!
0$
#279000
1!
1$
b10000010 )
b10000010 *
b1001 ,
#280000
0!
0$
#281000
1!
1$
b10000011 )
b10000011 *
b1010 ,
#282000
0!
0$
#283000
1!
b10100001 #
1$
b10100001 (
b10000100 )
b10000100 *
b1100 +
b0 ,
#284000
0!
0$
#285000
1!
1$
b10000101 )
b10000101 *
b1 ,
#286000
0!
0$
#287000
1!
1$
b10000110 )
b10000110 *
b10 ,
#288000
0!
0$
#289000
1!
1$
b10000111 )
b10000111 *
b11 ,
#290000
0!
0$
#291000
1!
1$
b10001000 )
b10001000 *
b100 ,
#292000
0!
0$
#293000
1!
1$
b10001001 )
b10001001 *
b101 ,
#294000
0!
0$
#295000
1!
1$
b10001010 )
b10001010 *
b110 ,
#296000
0!
0$
#297000
1!
1$
b10001011 )
b10001011 *
b111 ,
#298000
0!
0$
#299000
1!
1$
b10001100 )
b10001100 *
b1000 ,
#300000
0!
0$
#301000
1!
1$
b10001101 )
b10001101 *
b1001 ,
#302000
0!
0$
#303000
1!
1$
b10001110 )
b10001110 *
b1010 ,
#304000
0!
0$
#305000
1!
b10100100 #
1$
b10100100 (
b10001111 )
b10001111 *
b1101 +
b0 ,
#306000
0!
0$
#307000
1!
1$
b10010000 )
b10010000 *
b1 ,
#308000
0!
0$
#309000
1!
1$
b10010001 )
b10010001 *
b10 ,
#310000
0!
0$
#311000
1!
1$
b10010010 )
b10010010 *
b11 ,
#312000
0!
0$
#313000
1!
1$
b10010011 )
b10010011 *
b100 ,
#314000
0!
0$
#315000
1!
1$
b10010100 )
b10010100 *
b101 ,
#316000
0!
0$
#317000
1!
1$
b10010101 )
b10010101 *
b110 ,
#318000
0!
0$
#319000
1!
1$
b10010110 )
b10010110 *
b111 ,
#320000
0!
0$
#321000
1!
1$
b10010111 )
b10010111 *
b1000 ,
#322000
0!
0$
#323000
1!
1$
b10011000 )
b10011000 *
b1001 ,
#324000
0!
0$
#325000
1!
1$
b10011001 )
b10011001 *
b1010 ,
#326000
0!
0$
#327000
1!
b10100111 #
1$
b10100111 (
b10011010 )
b10011010 *
b1110 +
b0 ,
#328000
0!
0$
#329000
1!
1$
b10011011 )
b10011011 *
b1 ,
#330000
0!
0$
#331000
1!
1$
b10011100 )
b10011100 *
b10 ,
#332000
0!
0$
#333000
1!
1$
b10011101 )
b10011101 *
b11 ,
#334000
0!
0$
#335000
1!
1$
b10011110 )
b10011110 *
b100 ,
#336000
0!
0$
#337000
1!
1$
b10011111 )
b10011111 *
b101 ,
#338000
0!
0$
#339000
1!
1$
b10100000 )
b10100000 *
b110 ,
#340000
0!
0$
#341000
1!
1$
b10100001 )
b10100001 *
b111 ,
#342000
0!
0$
#343000
1!
1$
b10100010 )
b10100010 *
b1000 ,
#344000
0!
0$
#345000
1!
1$
b10100011 )
b10100011 *
b1001 ,
#346000
0!
0$
#347000
1!
1$
b10100100 )
b10100100 *
b1010 ,
#348000
0!
0$
#349000
1!
b10101010 #
1$
b10101010 (
b10100101 )
b10100101 *
b1111 +
b0 ,
#350000
0!
0$
#351000
1!
1$
b10100110 )
b10100110 *
b1 ,
#352000
0!
0$
#353000
1!
1$
b10100111 )
b10100111 *
b10 ,
#354000
0!
0$
#355000
1!
1$
b10101000 )
b10101000 *
b11 ,
#356000
0!
0$
#357000
1!
1$
b10101001 )
b10101001 *
b100 ,
#358000
0!
0$
#359000
1!
1$
b10101010 )
b10101010 *
b101 ,
#360000
0!
0$
#361000
1!
1$
b10101011 )
b10101011 *
b110 ,
#362000
0!
0$
#363000
1!
1$
b10101100 )
b10101100 *
b111 ,
#364000
0!
0$
#365000
1!
1$
b10101101 )
b10101101 *
b1000 ,
#366000
0!
0$
#367000
1!
1$
b10101110 )
b10101110 *
b1001 ,
#368000
0!
0$
#369000
1!
1$
b10101111 )
b10101111 *
b1010 ,
#370000
0!
0$
#371000
1!
b10101101 #
1$
b10101101 (
b10110000 )
b10110000 *
b10000 +
b0 ,
#372000
0!
0$
#373000
1!
1$
b10110001 )
b10110001 *
b1 ,
#374000
0!
0$
#375000
1!
1$
b10110010 )
b10110010 *
b10 ,
#376000
0!
0$
#377000
1!
1$
b10110011 )
b10110011 *
b11 ,
#378000
0!
0$
#379000
1!
1$
b10110100 )
b10110100 *
b100 ,
#380000
0!
0$
#381000
1!
1$
b10110101 )
b10110101 *
b101 ,
#382000
0!
0$
#383000
1!
1$
b10110110 )
b10110110 *
b110 ,
#384000
0!
0$
#385000
1!
1$
b10110111 )
b10110111 *
b111 ,
#386000
0!
0$
#387000
1!
1$
b10111000 )
b10111000 *
b1000 ,
#388000
0!
0$
#389000
1!
1$
b10111001 )
b10111001 *
b1001 ,
#390000
0!
0$
#391000
1!
1$
b10111010 )
b10111010 *
b1010 ,
#392000
0!
0$
#393000
1!
b10110000 #
1$
b10110000 (
b10111011 )
b10111011 *
b10001 +
b0 ,
#394000
0!
0$
#395000
1!
1$
b10111100 )
b10111100 *
b1 ,
#396000
0!
0$
#397000
1!
1$
b10111101 )
b10111101 *
b10 ,
#398000
0!
0$
#399000
1!
1$
b10111110 )
b10111110 *
b11 ,
#400000
0!
0$
#401000
1!
1$
b10111111 )
b10111111 *
b100 ,
#402000
0!
0$
#403000
1!
1$
b11000000 )
b11000000 *
b101 ,
#404000
0!
0$
#405000
1!
1$
b11000001 )
b11000001 *
b110 ,
#406000
0!
0$
#407000
1!
1$
b11000010 )
b11000010 *
b111 ,
#408000
0!
0$
#409000
1!
1$
b11000011 )
b11000011 *
b1000 ,
#410000
0!
0$
#411000
1!
1$
b11000100 )
b11000100 *
b1001 ,
#412000
0!
0$
#413000
1!
1$
b11000101 )
b11000101 *
b1010 ,
#414000
0!
0$
#415000
1!
b10110011 #
1$
b10110011 (
b11000110 )
b11000110 *
b10010 +
b0 ,
#416000
0!
0$
#417000
1!
1$
b11000111 )
b11000111 *
b1 ,
#418000
0!
0$
#419000
1!
1$
b11001000 )
b11001000 *
b10 ,
#420000
0!
0$
#421000
1!
1$
b11001001 )
b11001001 *
b11 ,
#422000
0!
0$
#423000
1!
1$
b11001010 )
b11001010 *
b100 ,
#424000
0!
0$
#425000
1!
1$
b11001011 )
b11001011 *
b101 ,
#426000
0!
0$
#427000
1!
1$
b11001100 )
b11001100 *
b110 ,
#428000
0!
0$
#429000
1!
1$
b11001101 )
b11001101 *
b111 ,
#430000
0!
0$
#431000
1!
1$
b11001110 )
b11001110 *
b1000 ,
#432000
0!
0$
#433000
1!
1$
b11001111 )
b11001111 *
b1001 ,
#434000
0!
0$
#435000
1!
1$
b11010000 )
b11010000 *
b1010 ,
#436000
0!
0$
#437000
1!
b10110110 #
1$
b10110110 (
b11010001 )
b11010001 *
b10011 +
b0 ,
#438000
0!
0$
#439000
1!
1$
b11010010 )
b11010010 *
b1 ,
#440000
0!
0$
#441000
1!
1$
b11010011 )
b11010011 *
b10 ,
#442000
0!
0$
#443000
1!
1$
b11010100 )
b11010100 *
b11 ,
#444000
0!
0$
#445000
1!
1$
b11010101 )
b11010101 *
b100 ,
#446000
0!
0$
#447000
1!
1$
b11010110 )
b11010110 *
b101 ,
#448000
0!
0$
#449000
1!
1$
b11010111 )
b11010111 *
b110 ,
#450000
0!
0$
#451000
1!
1$
b11011000 )
b11011000 *
b111 ,
#452000
0!
0$
#453000
1!
1$
b11011001 )
b11011001 *
b1000 ,
#454000
0!
0$
#455000
1!
1$
b11011010 )
b11011010 *
b1001 ,
#456000
0!
0$
#457000
1!
1$
b11011011 )
b11011011 *
b1010 ,
#458000
0!
0$
#459000
1!
b10111001 #
1$
b10111001 (
b11011100 )
b11011100 *
b10100 +
b0 ,
#460000
0!
0$
#461000
1!
1$
b11011101 )
b11011101 *
b1 ,
#462000
0!
0$
#463000
1!
1$
b11011110 )
b11011110 *
b10 ,
#464000
0!
0$
#465000
1!
1$
b11011111 )
b11011111 *
b11 ,
#466000
0!
0$
